README.rst
setup.cfg
setup.py
sphinxcontrib_dooble/__init__.py
sphinxcontrib_dooble/dooble.py
sphinxcontrib_dooble.egg-info/PKG-INFO
sphinxcontrib_dooble.egg-info/SOURCES.txt
sphinxcontrib_dooble.egg-info/dependency_links.txt
sphinxcontrib_dooble.egg-info/requires.txt
sphinxcontrib_dooble.egg-info/top_level.txt
sphinxcontrib_dooble.egg-info/zip-safe
tests/__init__.py