Metadata-Version: 1.1
Name: sphinxcontrib-dooble
Version: 1.0.0
Summary: A sphinx extansion for dooble
Home-page: https://github.com/mainro/sphinxcontrib-dooble
Author: Romain Picard
Author-email: romain.picard@oakbits.com
License: MIT license
Keywords: dooble,sphinx
Platform: UNKNOWN
Classifier: Development Status :: 2 - Pre-Alpha
Classifier: Intended Audience :: Developers
Classifier: License :: OSI Approved :: MIT License
Classifier: Natural Language :: English
Classifier: Programming Language :: Python :: 3
